Workbook

Sheet MAIN
A1: NVIDIA Corporation
B3: Company Name | C3: NVIDIA Corporation | F3: Current Stock Price | G3: =Assumptions!$C$18 -> 228 | I3: Perpetuity | J3: Exit Multiple | K3: Average
B4: Latest BS date | C4: 46230 | F4: Diluted S/O | G4: =Assumptions!$C$17 -> 24.2 | H4: Implied Price | I4: =DCF!C26 -> 214.0682 | J4: =DCF!E26 -> 289.0043 | K4: =AVERAGE(I4, J4) -> 251.53625
B5: Currency | C5: USD | F5: MKT cap | G5: =Assumptions!$C$18*Assumptions!$C$17 -> 5517.6 | H5: Difference | I5: =I4/$G$3-1 -> -0.061104375 | J5: =J4/G3-1 -> 0.26756274 | K5: =AVERAGE(I5, J5) -> 0.10322918
B6: Units | C6: b | F6: Net Cash | G6: =Assumptions!$C$16 -> 50.1
B7: Analyst Name | C7: Aleem Ahmad | F7: EV | G7: =DCF!$C$22 -> 5130.3505

Sheet Assumptions
A1: NVIDIA - DCF Assumption
A2: All figures in US% billion unless noted
A4: Time-Series Drivers | C4: FY2026A | D4: FY2027E | E4: FY2028E | F4: FY2029E | G4: FY2030E | H4: FY2031E
A5: Revenue Growth (%) | D5: 0.8 | E5: 0.45 | F5: 0.3 | G5: 0.22 | H5: 0.16
A6: Operating Margin % | C6: 0.604 | D6: 0.63 | E6: 0.625 | F6: 0.62 | G6: 0.61 | H6: 0.6
A7: CapEx % of Revenue | C7: 0.022 | D7: 0.022 | E7: 0.022 | F7: 0.022 | G7: 0.022 | H7: 0.022
A8: D&A % of Revenue | C8: 0.015 | D8: 0.015 | E8: 0.015 | F8: 0.015 | G8: 0.015 | H8: 0.015
A10: Single Value Asumptions | C10: Value
A11: Revenue FY2026A ($B) | C11: 215.9
A12: Effective Tax Rate | C12: 0.17
A13: Change in WC (% of Change in Revenue) | C13: 0.03
A14: Terminal Growth Rate | C14: 0.03
A15: Exit EV/EBITDA multiple | C15: 15
A16: Net Cash ($B) | C16: 50.1
A17: Diluted Shares (bn) | C17: 24.2
A18: Current Share Price ($) | C18: 228

Sheet WACC
A1: NVIDIA - WACC Build
A2: Cost of equity via CAPM; cost of debt post-tax; weighted by market values.
A4: Risk-Free Rate (10Y UST) | B4: 0.041
A5: Equity Risk Premium | B5: 0.05
A6: Levered Beta | B6: 1.38
A7: Cost of Equity | B7: =B4+B6*B5 -> 0.11
A8: Pre-tax Cost of Debt | B8: 0.04
A9: Tax Rate | B9: =Assumptions!C12 -> 0.17
A10: After-tax Cost of Debt | B10: =B8*(1-B9) -> 0.0332
A11: Market Cap $B) | B11: =Assumptions!C17*Assumptions!C18 -> 5517.6
A12: Gross Debt ($B) | B12: 10
A13: % Equity | B13: =B11/(B11+B12) -> 0.9981909
A14: % Debt | B14: =B12/(B11+B12) -> 0.0018091034
A15: WACC | B15: =(B7*B13)+(B10*B14) -> 0.10986106

Sheet DCF
A1: NVIDIA - Unlevered DCF
A3: US$ billions | B3: FY2026A | C3: FY2027E | D3: FY2028E | E3: FY2029E | F3: FY2030E | G3: FY2031E
A4: Revenue | B4: =Assumptions!C11 -> 215.9 | C4: =B4*(1+Assumptions!D5) -> 388.62 | D4: =C4*(1+Assumptions!E5) -> 563.499 | E4: =D4*(1+Assumptions!F5) -> 732.5487 | F4: =E4*(1+Assumptions!G5) -> 893.70941 | G4: =F4*(1+Assumptions!H5) -> 1036.7029
A5: y/y growth | C5: =Assumptions!D5 -> 0.8 | D5: =Assumptions!E5 -> 0.45 | E5: =Assumptions!F5 -> 0.3 | F5: =Assumptions!G5 -> 0.22 | G5: =Assumptions!H5 -> 0.16
A6: Operating Margin % | B6: =Assumptions!C6 -> 0.604 | C6: =Assumptions!D6 -> 0.63 | D6: =Assumptions!E6 -> 0.625 | E6: =Assumptions!F6 -> 0.62 | F6: =Assumptions!G6 -> 0.61 | G6: =Assumptions!H6 -> 0.6
A7: EBIT | B7: =B4*B6 -> 130.4036 | C7: =C4*C6 -> 244.8306 | D7: =D4*D6 -> 352.18687 | E7: =E4*E6 -> 454.18019 | F7: =F4*F6 -> 545.16274 | G7: =G4*G6 -> 622.02175
A8: Effective Tax Rate | B8: =Assumptions!$C$12 -> 0.17 | C8: =Assumptions!$C$12 -> 0.17 | D8: =Assumptions!$C$12 -> 0.17 | E8: =Assumptions!$C$12 -> 0.17 | F8: =Assumptions!$C$12 -> 0.17 | G8: =Assumptions!$C$12 -> 0.17
A9: NOPAT | B9: =B7*(1-B8) -> 108.23499 | C9: =C7*(1-C8) -> 203.2094 | D9: =D7*(1-D8) -> 292.31511 | E9: =E7*(1-E8) -> 376.96956 | F9: =F7*(1-F8) -> 452.48508 | G9: =G7*(1-G8) -> 516.27805
A10: (+)D&A | B10: =B4*Assumptions!C8 -> 3.2385 | C10: =C4*Assumptions!D8 -> 5.8293 | D10: =D4*Assumptions!E8 -> 8.452485 | E10: =E4*Assumptions!F8 -> 10.988231 | F10: =F4*Assumptions!G8 -> 13.405641 | G10: =G4*Assumptions!H8 -> 15.550544
A11: (-)CapEx | B11: =-B4*Assumptions!C7 -> -4.7498 | C11: =-C4*Assumptions!D7 -> -8.54964 | D11: =-D4*Assumptions!E7 -> -12.396978 | E11: =-E4*Assumptions!F7 -> -16.116071 | F11: =-F4*Assumptions!G7 -> -19.661607 | G11: =-G4*Assumptions!H7 -> -22.807464
A12: (-)Change in Working Capital | C12: =-Assumptions!$C$13*(C4-B4) -> -5.1816 | D12: =-Assumptions!$C$13*(D4-C4) -> -5.24637 | E12: =-Assumptions!$C$13*(E4-D4) -> -5.071491 | F12: =-Assumptions!$C$13*(F4-E4) -> -4.8348214 | G12: =-Assumptions!$C$13*(G4-F4) -> -4.2898052
A13: Free Cash Flow | B13: =B9+B10+B11 -> 106.72369 | C13: =C9+C10+C11+C12 -> 195.30746 | D13: =D9+D10+D11+D12 -> 283.12424 | E13: =E9+E10+E11+E12 -> 366.77023 | F13: =F9+F10+F11+F12 -> 441.39429 | G13: =G9+G10+G11+G12 -> 504.73133
A15: Discount Period | C15: 1 | D15: =C15+1 -> 2 | E15: =D15+1 -> 3 | F15: =E15+1 -> 4 | G15: =F15+1 -> 5
A16: Discount Factor | C16: =1/(1+WACC!$B$15)^C15 -> 0.90101368 | D16: =1/(1+WACC!$B$15)^D15 -> 0.81182565 | E16: =1/(1+WACC!$B$15)^E15 -> 0.73146602 | F16: =1/(1+WACC!$B$15)^F15 -> 0.65906089 | G16: =1/(1+WACC!$B$15)^G15 -> 0.59382288
A17: PV of FCF | C17: =C13*C16 -> 175.97469 | D17: =D13*D16 -> 229.84752 | E17: =E13*E16 -> 268.27996 | F17: =F13*F16 -> 290.90571 | G17: =G13*G16 -> 299.72101
A19: Valuation | C19: Perpetuity | E19: Exit Multiple
A20: Sum of PV of Explicit FCFs | C20: =SUM(C17:G17) -> 1264.7289 | E20: =C20 -> 1264.7289
A21: PV of terminal value | C21: =(G13*(1+Assumptions!$C$14)/(WACC!$B$15-Assumptions!$C$14))*G16 -> 3865.6216 | E21: =((G7+G10)*Assumptions!$C$15)*G16 -> 5679.0753
A22: Enterprise Value | C22: =C20+C21 -> 5130.3505 | E22: =E20+E21 -> 6943.8042
A23: (+) Net Cash | C23: =Assumptions!$C$16 -> 50.1 | E23: =Assumptions!$C$16 -> 50.1
A24: Equity Value | C24: =C22+C23 -> 5180.4505 | E24: =E22+E23 -> 6993.9042
A25: Diluted Shares | C25: =Assumptions!$C$17 -> 24.2 | E25: =Assumptions!$C$17 -> 24.2
A26: Implied Price per Share | C26: =C24/C25 -> 214.0682 | E26: =E24/E25 -> 289.0043
A27: Current Price | C27: =Assumptions!$C$18 -> 228 | E27: =Assumptions!$C$18 -> 228
A28: Upside/(Downside) | C28: =(C26/C27)-1 -> -0.061104375 | E28: =E26/E27-1 -> 0.26756274
A30: Method Reconciliation
A31: Perpetuity TV (undiscounted, $B) | C31: =G13*(1+Assumptions!$C$14)/(WACC!$B$15-Assumptions!$C$14) -> 6509.7215
A32: Exit TV (undiscounted, $B) | C32: =(G7+G10)*Assumptions!$C$15 -> 9563.5844
A33: Implied exit multiple (from 3.0% g) | C33: =C31/(G7+G10) -> 10.21017
A34: Implied terminal growth (from 15x) | C34: =(C32*WACC!$B$15-G13)/(G13+C32) -> 0.054222992
A36: Sensitivity - Implied Price / Share (exit multiple)
A37: WACC → / exit EV/EBITDA ↓ | C37: 0.1 | D37: 0.105 | E37: 0.11 | F37: 0.115 | G37: 0.12
B38: 11 | C38: {=(SUMPRODUCT($C$13:$G$13,1/(1+C$37)^(COLUMN($C$13:$G$13)-COLUMN($C$13)+1))+(($G$7+$G$10)*$B38)/(1+C$37)^5+Assumptions!$C$16)/Assumptions!$C$17} -> 235.81737 | D38: {=(SUMPRODUCT($C$13:$G$13,1/(1+D$37)^(COLUMN($C$13:$G$13)-COLUMN($C$13)+1))+(($G$7+$G$10)*$B38)/(1+D$37)^5+Assumptions!$C$16)/Assumptions!$C$17} -> 230.99418 | E38: {=(SUMPRODUCT($C$13:$G$13,1/(1+E$37)^(COLUMN($C$13:$G$13)-COLUMN($C$13)+1))+(($G$7+$G$10)*$B38)/(1+E$37)^5+Assumptions!$C$16)/Assumptions!$C$17} -> 226.29607 | F38: {=(SUMPRODUCT($C$13:$G$13,1/(1+F$37)^(COLUMN($C$13:$G$13)-COLUMN($C$13)+1))+(($G$7+$G$10)*$B38)/(1+F$37)^5+Assumptions!$C$16)/Assumptions!$C$17} -> 221.71922 | G38: {=(SUMPRODUCT($C$13:$G$13,1/(1+G$37)^(COLUMN($C$13:$G$13)-COLUMN($C$13)+1))+(($G$7+$G$10)*$B38)/(1+G$37)^5+Assumptions!$C$16)/Assumptions!$C$17} -> 217.25994
B39: 13 | C39: {=(SUMPRODUCT($C$13:$G$13,1/(1+C$37)^(COLUMN($C$13:$G$13)-COLUMN($C$13)+1))+(($G$7+$G$10)*$B39)/(1+C$37)^5+Assumptions!$C$16)/Assumptions!$C$17} -> 268.53491 | D39: {=(SUMPRODUCT($C$13:$G$13,1/(1+D$37)^(COLUMN($C$13:$G$13)-COLUMN($C$13)+1))+(($G$7+$G$10)*$B39)/(1+D$37)^5+Assumptions!$C$16)/Assumptions!$C$17} -> 262.97817 | E39: {=(SUMPRODUCT($C$13:$G$13,1/(1+E$37)^(COLUMN($C$13:$G$13)-COLUMN($C$13)+1))+(($G$7+$G$10)*$B39)/(1+E$37)^5+Assumptions!$C$16)/Assumptions!$C$17} -> 257.56616 | F39: {=(SUMPRODUCT($C$13:$G$13,1/(1+F$37)^(COLUMN($C$13:$G$13)-COLUMN($C$13)+1))+(($G$7+$G$10)*$B39)/(1+F$37)^5+Assumptions!$C$16)/Assumptions!$C$17} -> 252.29445 | G39: {=(SUMPRODUCT($C$13:$G$13,1/(1+G$37)^(COLUMN($C$13:$G$13)-COLUMN($C$13)+1))+(($G$7+$G$10)*$B39)/(1+G$37)^5+Assumptions!$C$16)/Assumptions!$C$17} -> 247.15876
B40: 15 | C40: {=(SUMPRODUCT($C$13:$G$13,1/(1+C$37)^(COLUMN($C$13:$G$13)-COLUMN($C$13)+1))+(($G$7+$G$10)*$B40)/(1+C$37)^5+Assumptions!$C$16)/Assumptions!$C$17} -> 301.25245 | D40: {=(SUMPRODUCT($C$13:$G$13,1/(1+D$37)^(COLUMN($C$13:$G$13)-COLUMN($C$13)+1))+(($G$7+$G$10)*$B40)/(1+D$37)^5+Assumptions!$C$16)/Assumptions!$C$17} -> 294.96216 | E40: {=(SUMPRODUCT($C$13:$G$13,1/(1+E$37)^(COLUMN($C$13:$G$13)-COLUMN($C$13)+1))+(($G$7+$G$10)*$B40)/(1+E$37)^5+Assumptions!$C$16)/Assumptions!$C$17} -> 288.83625 | F40: {=(SUMPRODUCT($C$13:$G$13,1/(1+F$37)^(COLUMN($C$13:$G$13)-COLUMN($C$13)+1))+(($G$7+$G$10)*$B40)/(1+F$37)^5+Assumptions!$C$16)/Assumptions!$C$17} -> 282.86968 | G40: {=(SUMPRODUCT($C$13:$G$13,1/(1+G$37)^(COLUMN($C$13:$G$13)-COLUMN($C$13)+1))+(($G$7+$G$10)*$B40)/(1+G$37)^5+Assumptions!$C$16)/Assumptions!$C$17} -> 277.05757
B41: 17 | C41: {=(SUMPRODUCT($C$13:$G$13,1/(1+C$37)^(COLUMN($C$13:$G$13)-COLUMN($C$13)+1))+(($G$7+$G$10)*$B41)/(1+C$37)^5+Assumptions!$C$16)/Assumptions!$C$17} -> 333.96999 | D41: {=(SUMPRODUCT($C$13:$G$13,1/(1+D$37)^(COLUMN($C$13:$G$13)-COLUMN($C$13)+1))+(($G$7+$G$10)*$B41)/(1+D$37)^5+Assumptions!$C$16)/Assumptions!$C$17} -> 326.94615 | E41: {=(SUMPRODUCT($C$13:$G$13,1/(1+E$37)^(COLUMN($C$13:$G$13)-COLUMN($C$13)+1))+(($G$7+$G$10)*$B41)/(1+E$37)^5+Assumptions!$C$16)/Assumptions!$C$17} -> 320.10635 | F41: {=(SUMPRODUCT($C$13:$G$13,1/(1+F$37)^(COLUMN($C$13:$G$13)-COLUMN($C$13)+1))+(($G$7+$G$10)*$B41)/(1+F$37)^5+Assumptions!$C$16)/Assumptions!$C$17} -> 313.44491 | G41: {=(SUMPRODUCT($C$13:$G$13,1/(1+G$37)^(COLUMN($C$13:$G$13)-COLUMN($C$13)+1))+(($G$7+$G$10)*$B41)/(1+G$37)^5+Assumptions!$C$16)/Assumptions!$C$17} -> 306.95638
B42: 19 | C42: {=(SUMPRODUCT($C$13:$G$13,1/(1+C$37)^(COLUMN($C$13:$G$13)-COLUMN($C$13)+1))+(($G$7+$G$10)*$B42)/(1+C$37)^5+Assumptions!$C$16)/Assumptions!$C$17} -> 366.68753 | D42: {=(SUMPRODUCT($C$13:$G$13,1/(1+D$37)^(COLUMN($C$13:$G$13)-COLUMN($C$13)+1))+(($G$7+$G$10)*$B42)/(1+D$37)^5+Assumptions!$C$16)/Assumptions!$C$17} -> 358.93015 | E42: {=(SUMPRODUCT($C$13:$G$13,1/(1+E$37)^(COLUMN($C$13:$G$13)-COLUMN($C$13)+1))+(($G$7+$G$10)*$B42)/(1+E$37)^5+Assumptions!$C$16)/Assumptions!$C$17} -> 351.37644 | F42: {=(SUMPRODUCT($C$13:$G$13,1/(1+F$37)^(COLUMN($C$13:$G$13)-COLUMN($C$13)+1))+(($G$7+$G$10)*$B42)/(1+F$37)^5+Assumptions!$C$16)/Assumptions!$C$17} -> 344.02014 | G42: {=(SUMPRODUCT($C$13:$G$13,1/(1+G$37)^(COLUMN($C$13:$G$13)-COLUMN($C$13)+1))+(($G$7+$G$10)*$B42)/(1+G$37)^5+Assumptions!$C$16)/Assumptions!$C$17} -> 336.8552
